rcft_pymarkdown/__init__.py
rcft_pymarkdown/__main__.py
rcft_pymarkdown/console.py
rcft_pymarkdown/context_manager.py
rcft_pymarkdown/remove_custom_formatted_tables.py
rcft_pymarkdown/restore_custom_formatted_tables.py
rcft_pymarkdown/utils/__init__.py
rcft_pymarkdown-1.0.4.dist-info/LICENSE
rcft_pymarkdown-1.0.4.dist-info/METADATA
rcft_pymarkdown-1.0.4.dist-info/WHEEL
rcft_pymarkdown-1.0.4.dist-info/entry_points.txt
rcft_pymarkdown-1.0.4.dist-info/RECORD
