Metadata-Version: 2.1
Name: RCFT-PyMarkdown
Version: 1.0.4
Summary: A Python wrapper around jackdewinter's PyMarkdown linter to remove custom tables in Markdown files
Home-page: https://github.com/CarrotManMatt/rcft-pymarkdown.git
License: Apache-2.0
Keywords: markdown,linter,static analysis
Author: CarrotManMatt
Author-email: matt@carrotmanmatt.com
Requires-Python: >=3.12,<4.0
Classifier: Development Status :: 4 - Beta
Classifier: Environment :: Console
Classifier: Intended Audience :: Developers
Classifier: License :: OSI Approved :: Apache Software License
Classifier: Natural Language :: English
Classifier: Operating System :: OS Independent
Classifier: Programming Language :: Python :: 3
Classifier: Programming Language :: Python :: 3.12
Classifier: Topic :: Software Development :: Quality Assurance
Classifier: Topic :: Text Processing :: Markup :: Markdown
Classifier: Typing :: Typed
Requires-Dist: gitpython (>=3.1,<4.0)
Requires-Dist: marko (>=2.0,<3.0)
Requires-Dist: pymarkdownlnt (>=0.9,<0.10)
Requires-Dist: setuptools (>=69.5,<70.0)
Project-URL: Repository, https://github.com/CarrotManMatt/rcft-pymarkdown.git
